handler/__init__.py
MessageHandler-1.0.2.dist-info/METADATA
MessageHandler-1.0.2.dist-info/WHEEL
MessageHandler-1.0.2.dist-info/top_level.txt
MessageHandler-1.0.2.dist-info/RECORD
