Metadata-Version: 2.1
Name: MessageHandler
Version: 1.0.2
Summary: A Command-like discord message handler for discord.
Home-page: https://github.com/Tim232/MessageHandler
Author: Tim232
Author-email: endbot4023@gmail.com
License: Apache License 2.0
Platform: UNKNOWN
Classifier: Programming Language :: Python :: 3
Classifier: License :: OSI Approved :: Apache Software License
Classifier: Operating System :: OS Independent
